[
  {
    "LocationName": "SquashBusters - 4th Floor",
    "CountOfParticipants": 20,
    "PercetageCapacity": 33,
    "IsClosed": false,
    "FacilityId": 999,
    "FacilityName": "SquashBusters",
    "LastUpdatedDateAndTime": "2026-05-20T23:59:00.000Z",
    "FetchedAt": "2026-05-21T00:28:20.317Z"
  },
  {
    "LocationName": "Studio A",
    "CountOfParticipants": 14,
    "PercetageCapacity": 42,
    "IsClosed": false,
    "FacilityId": 1068,
    "FacilityName": "UREC",
    "LastUpdatedDateAndTime": "2026-05-21T00:07:00.000Z",
    "FetchedAt": "2026-05-21T00:28:20.317Z"
  },
  {
    "LocationName": "Studio B",
    "CountOfParticipants": 14,
    "PercetageCapacity": 42,
    "IsClosed": false,
    "FacilityId": 1068,
    "FacilityName": "UREC",
    "LastUpdatedDateAndTime": "2026-05-21T00:07:00.000Z",
    "FetchedAt": "2026-05-21T00:28:20.317Z"
  },
  {
    "LocationName": "2nd Floor",
    "CountOfParticipants": 49,
    "PercetageCapacity": 47,
    "IsClosed": false,
    "FacilityId": 1068,
    "FacilityName": "UREC",
    "LastUpdatedDateAndTime": "2026-05-21T00:07:00.000Z",
    "FetchedAt": "2026-05-21T00:28:20.317Z"
  },
  {
    "LocationName": "Gymnasium",
    "CountOfParticipants": 47,
    "PercetageCapacity": 78,
    "IsClosed": false,
    "FacilityId": 1068,
    "FacilityName": "UREC",
    "LastUpdatedDateAndTime": "2026-05-21T00:07:00.000Z",
    "FetchedAt": "2026-05-21T00:28:20.317Z"
  },
  {
    "LocationName": "3rd Floor Weight Room",
    "CountOfParticipants": 50,
    "PercetageCapacity": 77,
    "IsClosed": false,
    "FacilityId": 1068,
    "FacilityName": "UREC",
    "LastUpdatedDateAndTime": "2026-05-20T23:32:00.000Z",
    "FetchedAt": "2026-05-21T00:28:20.317Z"
  },
  {
    "LocationName": "3rd Floor Select & Cardio",
    "CountOfParticipants": 49,
    "PercetageCapacity": 54,
    "IsClosed": false,
    "FacilityId": 1068,
    "FacilityName": "UREC",
    "LastUpdatedDateAndTime": "2026-05-20T23:32:00.000Z",
    "FetchedAt": "2026-05-21T00:28:20.317Z"
  },
  {
    "LocationName": "1st Floor Weight Room",
    "CountOfParticipants": 13,
    "PercetageCapacity": 37,
    "IsClosed": false,
    "FacilityId": 1068,
    "FacilityName": "UREC",
    "LastUpdatedDateAndTime": "2026-05-21T00:02:00.000Z",
    "FetchedAt": "2026-05-21T00:28:20.317Z"
  }
]