[
  {
    "LocationName": "SquashBusters - 4th Floor",
    "CountOfParticipants": 0,
    "PercetageCapacity": 0,
    "IsClosed": false,
    "FacilityId": 999,
    "FacilityName": "SquashBusters",
    "LastUpdatedDateAndTime": "2026-05-08T21:56:00.000Z",
    "FetchedAt": "2026-05-08T22:20:32.941Z"
  },
  {
    "LocationName": "Studio A",
    "CountOfParticipants": 3,
    "PercetageCapacity": null,
    "IsClosed": true,
    "FacilityId": 1068,
    "FacilityName": "UREC",
    "LastUpdatedDateAndTime": "2026-05-08T21:30:00.000Z",
    "FetchedAt": "2026-05-08T22:20:32.941Z"
  },
  {
    "LocationName": "Studio B",
    "CountOfParticipants": 12,
    "PercetageCapacity": 36,
    "IsClosed": false,
    "FacilityId": 1068,
    "FacilityName": "UREC",
    "LastUpdatedDateAndTime": "2026-05-08T22:02:00.000Z",
    "FetchedAt": "2026-05-08T22:20:32.941Z"
  },
  {
    "LocationName": "2nd Floor",
    "CountOfParticipants": 42,
    "PercetageCapacity": 40,
    "IsClosed": false,
    "FacilityId": 1068,
    "FacilityName": "UREC",
    "LastUpdatedDateAndTime": "2026-05-08T22:02:00.000Z",
    "FetchedAt": "2026-05-08T22:20:32.941Z"
  },
  {
    "LocationName": "Gymnasium",
    "CountOfParticipants": 46,
    "PercetageCapacity": 77,
    "IsClosed": false,
    "FacilityId": 1068,
    "FacilityName": "UREC",
    "LastUpdatedDateAndTime": "2026-05-08T22:02:00.000Z",
    "FetchedAt": "2026-05-08T22:20:32.941Z"
  },
  {
    "LocationName": "3rd Floor Weight Room",
    "CountOfParticipants": 46,
    "PercetageCapacity": 71,
    "IsClosed": false,
    "FacilityId": 1068,
    "FacilityName": "UREC",
    "LastUpdatedDateAndTime": "2026-05-08T21:57:00.000Z",
    "FetchedAt": "2026-05-08T22:20:32.941Z"
  },
  {
    "LocationName": "3rd Floor Select & Cardio",
    "CountOfParticipants": 42,
    "PercetageCapacity": 47,
    "IsClosed": false,
    "FacilityId": 1068,
    "FacilityName": "UREC",
    "LastUpdatedDateAndTime": "2026-05-08T21:57:00.000Z",
    "FetchedAt": "2026-05-08T22:20:32.941Z"
  },
  {
    "LocationName": "1st Floor Weight Room",
    "CountOfParticipants": 15,
    "PercetageCapacity": 43,
    "IsClosed": false,
    "FacilityId": 1068,
    "FacilityName": "UREC",
    "LastUpdatedDateAndTime": "2026-05-08T22:05:00.000Z",
    "FetchedAt": "2026-05-08T22:20:32.941Z"
  }
]