[
  {
    "LocationName": "SquashBusters - 4th Floor",
    "CountOfParticipants": 0,
    "PercetageCapacity": 0,
    "IsClosed": false,
    "FacilityId": 999,
    "FacilityName": "SquashBusters",
    "LastUpdatedDateAndTime": "2026-05-22T21:59:00.000Z",
    "FetchedAt": "2026-05-24T16:34:23.311Z"
  },
  {
    "LocationName": "Studio A",
    "CountOfParticipants": 3,
    "PercetageCapacity": 9,
    "IsClosed": false,
    "FacilityId": 1068,
    "FacilityName": "UREC",
    "LastUpdatedDateAndTime": "2026-05-23T22:16:00.000Z",
    "FetchedAt": "2026-05-24T16:34:23.311Z"
  },
  {
    "LocationName": "Studio B",
    "CountOfParticipants": 3,
    "PercetageCapacity": 9,
    "IsClosed": false,
    "FacilityId": 1068,
    "FacilityName": "UREC",
    "LastUpdatedDateAndTime": "2026-05-23T22:16:00.000Z",
    "FetchedAt": "2026-05-24T16:34:23.311Z"
  },
  {
    "LocationName": "2nd Floor",
    "CountOfParticipants": 25,
    "PercetageCapacity": 24,
    "IsClosed": false,
    "FacilityId": 1068,
    "FacilityName": "UREC",
    "LastUpdatedDateAndTime": "2026-05-23T22:16:00.000Z",
    "FetchedAt": "2026-05-24T16:34:23.311Z"
  },
  {
    "LocationName": "Gymnasium",
    "CountOfParticipants": 18,
    "PercetageCapacity": 30,
    "IsClosed": false,
    "FacilityId": 1068,
    "FacilityName": "UREC",
    "LastUpdatedDateAndTime": "2026-05-23T22:16:00.000Z",
    "FetchedAt": "2026-05-24T16:34:23.311Z"
  },
  {
    "LocationName": "3rd Floor Weight Room",
    "CountOfParticipants": 26,
    "PercetageCapacity": 40,
    "IsClosed": false,
    "FacilityId": 1068,
    "FacilityName": "UREC",
    "LastUpdatedDateAndTime": "2026-05-24T16:27:00.000Z",
    "FetchedAt": "2026-05-24T16:34:23.311Z"
  },
  {
    "LocationName": "3rd Floor Select & Cardio",
    "CountOfParticipants": 21,
    "PercetageCapacity": 23,
    "IsClosed": false,
    "FacilityId": 1068,
    "FacilityName": "UREC",
    "LastUpdatedDateAndTime": "2026-05-24T16:27:00.000Z",
    "FetchedAt": "2026-05-24T16:34:23.311Z"
  },
  {
    "LocationName": "1st Floor Weight Room",
    "CountOfParticipants": 7,
    "PercetageCapacity": 20,
    "IsClosed": false,
    "FacilityId": 1068,
    "FacilityName": "UREC",
    "LastUpdatedDateAndTime": "2026-05-24T16:30:00.000Z",
    "FetchedAt": "2026-05-24T16:34:23.311Z"
  }
]