[
  {
    "LocationName": "SquashBusters - 4th Floor",
    "CountOfParticipants": 16,
    "PercetageCapacity": 27,
    "IsClosed": false,
    "FacilityId": 999,
    "FacilityName": "SquashBusters",
    "LastUpdatedDateAndTime": "2026-05-07T23:27:00.000Z",
    "FetchedAt": "2026-05-08T00:01:27.121Z"
  },
  {
    "LocationName": "Studio A",
    "CountOfParticipants": 3,
    "PercetageCapacity": 9,
    "IsClosed": false,
    "FacilityId": 1068,
    "FacilityName": "UREC",
    "LastUpdatedDateAndTime": "2026-05-07T23:44:00.000Z",
    "FetchedAt": "2026-05-08T00:01:27.121Z"
  },
  {
    "LocationName": "Studio B",
    "CountOfParticipants": 4,
    "PercetageCapacity": 12,
    "IsClosed": false,
    "FacilityId": 1068,
    "FacilityName": "UREC",
    "LastUpdatedDateAndTime": "2026-05-07T23:44:00.000Z",
    "FetchedAt": "2026-05-08T00:01:27.121Z"
  },
  {
    "LocationName": "2nd Floor",
    "CountOfParticipants": 53,
    "PercetageCapacity": 50,
    "IsClosed": false,
    "FacilityId": 1068,
    "FacilityName": "UREC",
    "LastUpdatedDateAndTime": "2026-05-07T23:44:00.000Z",
    "FetchedAt": "2026-05-08T00:01:27.121Z"
  },
  {
    "LocationName": "Gymnasium",
    "CountOfParticipants": 37,
    "PercetageCapacity": 62,
    "IsClosed": false,
    "FacilityId": 1068,
    "FacilityName": "UREC",
    "LastUpdatedDateAndTime": "2026-05-07T23:44:00.000Z",
    "FetchedAt": "2026-05-08T00:01:27.121Z"
  },
  {
    "LocationName": "3rd Floor Weight Room",
    "CountOfParticipants": 49,
    "PercetageCapacity": 75,
    "IsClosed": false,
    "FacilityId": 1068,
    "FacilityName": "UREC",
    "LastUpdatedDateAndTime": "2026-05-07T23:52:00.000Z",
    "FetchedAt": "2026-05-08T00:01:27.121Z"
  },
  {
    "LocationName": "3rd Floor Select & Cardio",
    "CountOfParticipants": 27,
    "PercetageCapacity": 30,
    "IsClosed": false,
    "FacilityId": 1068,
    "FacilityName": "UREC",
    "LastUpdatedDateAndTime": "2026-05-07T23:42:00.000Z",
    "FetchedAt": "2026-05-08T00:01:27.121Z"
  },
  {
    "LocationName": "1st Floor Weight Room",
    "CountOfParticipants": 17,
    "PercetageCapacity": 49,
    "IsClosed": false,
    "FacilityId": 1068,
    "FacilityName": "UREC",
    "LastUpdatedDateAndTime": "2026-05-08T00:00:00.000Z",
    "FetchedAt": "2026-05-08T00:01:27.121Z"
  }
]