[
  {
    "LocationName": "SquashBusters - 4th Floor",
    "CountOfParticipants": 0,
    "PercetageCapacity": 0,
    "IsClosed": false,
    "FacilityId": 999,
    "FacilityName": "SquashBusters",
    "LastUpdatedDateAndTime": "2026-05-01T22:02:00.000Z",
    "FetchedAt": "2026-05-04T00:57:20.102Z"
  },
  {
    "LocationName": "Studio A",
    "CountOfParticipants": 1,
    "PercetageCapacity": 3,
    "IsClosed": false,
    "FacilityId": 1068,
    "FacilityName": "UREC",
    "LastUpdatedDateAndTime": "2026-05-04T00:35:00.000Z",
    "FetchedAt": "2026-05-04T00:57:20.102Z"
  },
  {
    "LocationName": "Studio B",
    "CountOfParticipants": 3,
    "PercetageCapacity": 9,
    "IsClosed": false,
    "FacilityId": 1068,
    "FacilityName": "UREC",
    "LastUpdatedDateAndTime": "2026-05-04T00:35:00.000Z",
    "FetchedAt": "2026-05-04T00:57:20.102Z"
  },
  {
    "LocationName": "2nd Floor",
    "CountOfParticipants": 16,
    "PercetageCapacity": 15,
    "IsClosed": false,
    "FacilityId": 1068,
    "FacilityName": "UREC",
    "LastUpdatedDateAndTime": "2026-05-04T00:35:00.000Z",
    "FetchedAt": "2026-05-04T00:57:20.102Z"
  },
  {
    "LocationName": "Gymnasium",
    "CountOfParticipants": 21,
    "PercetageCapacity": 35,
    "IsClosed": false,
    "FacilityId": 1068,
    "FacilityName": "UREC",
    "LastUpdatedDateAndTime": "2026-05-04T00:35:00.000Z",
    "FetchedAt": "2026-05-04T00:57:20.102Z"
  },
  {
    "LocationName": "3rd Floor Weight Room",
    "CountOfParticipants": 17,
    "PercetageCapacity": 26,
    "IsClosed": false,
    "FacilityId": 1068,
    "FacilityName": "UREC",
    "LastUpdatedDateAndTime": "2026-05-04T00:35:00.000Z",
    "FetchedAt": "2026-05-04T00:57:20.102Z"
  },
  {
    "LocationName": "3rd Floor Select & Cardio",
    "CountOfParticipants": 24,
    "PercetageCapacity": 27,
    "IsClosed": false,
    "FacilityId": 1068,
    "FacilityName": "UREC",
    "LastUpdatedDateAndTime": "2026-05-04T00:35:00.000Z",
    "FetchedAt": "2026-05-04T00:57:20.102Z"
  },
  {
    "LocationName": "1st Floor Weight Room",
    "CountOfParticipants": 2,
    "PercetageCapacity": 6,
    "IsClosed": false,
    "FacilityId": 1068,
    "FacilityName": "UREC",
    "LastUpdatedDateAndTime": "2026-05-04T00:35:00.000Z",
    "FetchedAt": "2026-05-04T00:57:20.102Z"
  }
]